counter_paсk/__init__.py
counter_paсk/counter.py
counter_paсk/custom_exceptions.py
counter_pack-0.0.9.dist-info/METADATA
counter_pack-0.0.9.dist-info/WHEEL
counter_pack-0.0.9.dist-info/licenses/LICENSE
counter_pack-0.0.9.dist-info/RECORD
