Metadata-Version: 2.1
Name: counter_pack
Version: 0.0.9
Summary: A small package for counting unique characters in a string or text file
Author-email: Oleh Holub <golub.zp@google.com>
License: Copyright (c) 2018 The Python Packaging Authority
Classifier: License :: OSI Approved :: MIT License
Classifier: Operating System :: OS Independent
Classifier: Programming Language :: Python :: 3
Requires-Python: >=3.8
